LICENSE
MANIFEST.in
README.md
requirements.txt
setup.cfg
setup.py
versioneer.py
survivalstan/__init__.py
survivalstan/_version.py
survivalstan/formulas.py
survivalstan/models.py
survivalstan/sim.py
survivalstan/survivalstan.py
survivalstan/utils.py
survivalstan.egg-info/PKG-INFO
survivalstan.egg-info/SOURCES.txt
survivalstan.egg-info/dependency_links.txt
survivalstan.egg-info/requires.txt
survivalstan.egg-info/top_level.txt
survivalstan/stan/exp_survival_model.stan
survivalstan/stan/pem_survival_model.stan
survivalstan/stan/pem_survival_model_gamma.stan
survivalstan/stan/pem_survival_model_randomwalk.stan
survivalstan/stan/pem_survival_model_tvc.stan
survivalstan/stan/pem_survival_model_unstructured.stan
survivalstan/stan/pem_survival_model_unstructured_varcoef.stan
survivalstan/stan/pem_survival_model_varying_coefs.stan
survivalstan/stan/pem_survival_model_varying_coefs2.stan
survivalstan/stan/pem_survival_model_varying_coefs3.stan
survivalstan/stan/pem_survival_model_varying_coefs4.stan
survivalstan/stan/weibull_survival_model.stan
survivalstan/stan/weibull_survival_model_varying_coefs.stan
test/test_SurvivalStanData.py
test/test_byo-gamma_survival_model.py
test/test_byo-gamma_survival_model_sim.py
test/test_datasets.py
test/test_exp_survival_model.py
test/test_exp_survival_model_sim.py
test/test_formulas.py
test/test_jointmodel_datasets.py
test/test_pem_survival_model.py
test/test_pem_survival_model_sim.py
test/test_pem_survival_model_timevarying.py
test/test_pem_survival_model_timevarying_sim.py
test/test_pem_survival_model_varcoefs.py
test/test_pem_survival_model_varcoefs_sim.py
test/test_weibull_survival_model.py
test/test_weibull_survival_model_sim.py