Metadata-Version: 1.1
Name: survivalstan
Version: 0.1.2.8
Summary: Library of Stan Models for Survival Analysis
Home-page: https://github.com/hammerlab/survivalstan
Author: Jacki Novik
Author-email: jackinovik@gmail.com
License: http://www.apache.org/licenses/LICENSE-2.0.html
Download-URL: https://github.com/hammerlab/survivalstan/tarball/0.1.2.8
Platform: UNKNOWN
Classifier: Development Status :: 3 - Alpha
Classifier: Environment :: Console
Classifier: Operating System :: OS Independent
Classifier: Intended Audience :: Science/Research
Classifier: License :: OSI Approved :: Apache Software License
Classifier: Programming Language :: Python
Classifier: Topic :: Scientific/Engineering :: Bio-Informatics
